{"id": "0", "input": "Reyes tricked into Real admission  Jose Antonio Reyes has added to speculation linking him with a move from Arsenal to Real Madrid after falling victim to a radio prank.", "nodes": [{"id": 0}, {"id": 1, "label": "\"now\""}, {"id": 2, "label": "\"reyes\""}, {"id": 3, "label": "time.n.08"}, {"id": 4, "label": "trick.v.01"}, {"id": 5, "label": "\"real\""}, {"id": 6, "label": "admission.n.01"}, {"id": 7, "label": "\"jose~antonio~reyes\""}, {"id": 8, "label": "time.n.08"}, {"id": 9, "label": "add.v.02"}, {"id": 10, "label": "speculation.n.01"}, {"id": 11, "label": "link.v.01"}, {"id": 12, "label": "move.n.01"}, {"id": 13}, {"id": 14, "label": "state.n.04"}, {"id": 15, "label": "\"arsenal\""}, {"id": 16, "label": "team.n.01"}, {"id": 17, "label": "\"real~madrid\""}, {"id": 18}, {"id": 19, "label": "fall.v.01"}, {"id": 20, "label": "person.n.01"}, {"id": 21, "label": "victim.n.01"}, {"id": 22, "label": "radio.n.01"}, {"id": 23, "label": "prank.n.01"}, {"id": 24}, {"id": 25, "label": "male.n.02"}, {"id": 26, "label": "TPR"}, {"id": 27, "label": "PATIENT"}, {"id": 28, "label": "TPR"}, {"id": 29, "label": "TIME"}, {"id": 30, "label": "TIME"}, {"id": 31, "label": "NAME"}, {"id": 32, "label": "NAME"}, {"id": 33, "label": "AGENT"}, {"id": 34, "label": "TIME"}, {"id": 35, "label": "TIME"}, {"id": 36, "label": "AGENT"}, {"id": 37, "label": "PATIENT"}, {"id": 38, "label": "NAME"}, {"id": 39, "label": "THEME"}, {"id": 40, "label": "NAME"}, {"id": 41, "label": "AGENT"}], "edges": [{"source": 3, "target": 26}, {"source": 26, "target": 1}, {"source": 4, "target": 27}, {"source": 27, "target": 25}, {"source": 24, "target": 25, "label": "in"}, {"source": 8, "target": 28}, {"source": 28, "target": 1}, {"source": 4, "target": 29}, {"source": 29, "target": 3}, {"source": 9, "target": 30}, {"source": 30, "target": 8}, {"source": 0, "target": 12, "label": "in"}, {"source": 18, "target": 0, "label": "presupposition"}, {"source": 0, "target": 8, "label": "in"}, {"source": 16, "target": 31}, {"source": 31, "target": 17}, {"source": 14, "target": 32}, {"source": 32, "target": 15}, {"source": 13, "target": 0, "label": "presupposition"}, {"source": 24, "target": 0, "label": "presupposition"}, {"source": 23, "target": 33}, {"source": 33, "target": 22}, {"source": 0, "target": 4, "label": "in"}, {"source": 4, "target": 34}, {"source": 34, "target": 8}, {"source": 0, "target": 23, "label": "in"}, {"source": 9, "target": 35}, {"source": 35, "target": 3}, {"source": 4, "target": 36}, {"source": 36, "target": 6}, {"source": 4, "target": 37}, {"source": 37, "target": 14}, {"source": 0, "target": 20, "label": "in"}, {"source": 0, "target": 9, "label": "in"}, {"source": 25, "target": 38}, {"source": 38, "target": 2}, {"source": 11, "target": 39}, {"source": 39, "target": 25}, {"source": 0, "target": 11, "label": "in"}, {"source": 0, "target": 3, "label": "in"}, {"source": 0, "target": 22, "label": "in"}, {"source": 14, "target": 40}, {"source": 40, "target": 5}, {"source": 9, "target": 41}, {"source": 41, "target": 25}, {"source": 13, "target": 14, "label": "in"}, {"source": 0, "target": 21, "label": "in"}], "tops": [0], "framework": "drg", "time": "2025-04-11"}
{"id": "1", "input": "The Spaniard believed he was talking to Real Madrid sporting director Emilio Butragueno when he allegedly berated his team-mates as \"bad people\".", "nodes": [{"id": 0}, {"id": 1, "label": "\"now\""}, {"id": 2, "label": "person.n.01"}, {"id": 3}, {"id": 4, "label": "country.n.02"}, {"id": 5, "label": "\"spanland\""}, {"id": 6, "label": "time.n.08"}, {"id": 7, "label": "believe.v.01"}, {"id": 8, "label": "proposition.n.01"}, {"id": 9}, {"id": 10, "label": "time.n.08"}, {"id": 11, "label": "talk.v.04"}, {"id": 12, "label": "musical_organization.n.01"}, {"id": 13, "label": "\"real~madrid\""}, {"id": 14}, {"id": 15, "label": "sporting.a.05"}, {"id": 16, "label": "male.n.02"}, {"id": 17, "label": "\"emilio~butragueno\""}, {"id": 18}, {"id": 19, "label": "allegedly.r.01"}, {"id": 20, "label": "berate.v.04"}, {"id": 21, "label": "team.n.01"}, {"id": 22, "label": "person.n.01"}, {"id": 23, "label": "mate.n.01"}, {"id": 24, "label": "bad.a.02"}, {"id": 25, "label": "person.n.01"}, {"id": 26}, {"id": 27, "label": "male.n.02"}, {"id": 28, "label": "TIME"}, {"id": 29, "label": "ROLE"}, {"id": 30, "label": "TPR"}, {"id": 31, "label": "THEME"}, {"id": 32, "label": "AGENT"}, {"id": 33, "label": "STIMULUS"}, {"id": 34, "label": "AGENT"}, {"id": 35, "label": "TIME"}, {"id": 36, "label": "AGENT"}, {"id": 37, "label": "OF"}, {"id": 38, "label": "TPR"}, {"id": 39, "label": "NAME"}, {"id": 40, "label": "AGENT"}, {"id": 41, "label": "AGENT"}, {"id": 42, "label": "CO-AGENT"}, {"id": 43, "label": "TIME"}, {"id": 44, "label": "CO-AGENT"}, {"id": 45, "label": "ROLE"}, {"id": 46, "label": "AGENT"}, {"id": 47, "label": "NAME"}, {"id": 48, "label": "TIME"}, {"id": 49, "label": "AGENT"}, {"id": 50, "label": "NAME"}, {"id": 51, "label": "AGENT"}, {"id": 52, "label": "TIME"}, {"id": 53, "label": "CO-AGENT"}, {"id": 54, "label": "AGENT"}, {"id": 55, "label": "NAME"}], "edges": [{"source": 7, "target": 28}, {"source": 28, "target": 6}, {"source": 2, "target": 29}, {"source": 29, "target": 4}, {"source": 10, "target": 30}, {"source": 30, "target": 1}, {"source": 21, "target": 31}, {"source": 31, "target": 27}, {"source": 9, "target": 8, "label": "in"}, {"source": 7, "target": 32}, {"source": 32, "target": 27}, {"source": 0, "target": 11, "label": "in"}, {"source": 7, "target": 33}, {"source": 33, "target": 8}, {"source": 20, "target": 34}, {"source": 34, "target": 2}, {"source": 11, "target": 35}, {"source": 35, "target": 6}, {"source": 7, "target": 36}, {"source": 36, "target": 2}, {"source": 23, "target": 37}, {"source": 37, "target": 27}, {"source": 6, "target": 38}, {"source": 38, "target": 1}, {"source": 0, "target": 25, "label": "in"}, {"source": 26, "target": 27, "label": "in"}, {"source": 4, "target": 39}, {"source": 39, "target": 5}, {"source": 20, "target": 40}, {"source": 40, "target": 27}, {"source": 9, "target": 7, "label": "in"}, {"source": 9, "target": 6, "label": "in"}, {"source": 11, "target": 41}, {"source": 41, "target": 27}, {"source": 11, "target": 42}, {"source": 42, "target": 22}, {"source": 9, "target": 0, "label": "attribution"}, {"source": 11, "target": 43}, {"source": 43, "target": 10}, {"source": 11, "target": 44}, {"source": 44, "target": 25}, {"source": 22, "target": 45}, {"source": 45, "target": 23}, {"source": 11, "target": 46}, {"source": 46, "target": 2}, {"source": 16, "target": 47}, {"source": 47, "target": 17}, {"source": 20, "target": 48}, {"source": 48, "target": 6}, {"source": 0, "target": 20, "label": "in"}, {"source": 18, "target": 0, "label": "presupposition"}, {"source": 20, "target": 49}, {"source": 49, "target": 22}, {"source": 12, "target": 50}, {"source": 50, "target": 13}, {"source": 0, "target": 24, "label": "in"}, {"source": 26, "target": 9, "label": "presupposition"}, {"source": 20, "target": 51}, {"source": 51, "target": 25}, {"source": 3, "target": 9, "label": "presupposition"}, {"source": 20, "target": 52}, {"source": 52, "target": 10}, {"source": 11, "target": 53}, {"source": 53, "target": 16}, {"source": 18, "target": 12, "label": "in"}, {"source": 14, "target": 12, "label": "in"}, {"source": 9, "target": 19, "label": "in"}, {"source": 20, "target": 54}, {"source": 54, "target": 16}, {"source": 14, "target": 9, "label": "presupposition"}, {"source": 9, "target": 2, "label": "in"}, {"source": 14, "target": 0, "label": "presupposition"}, {"source": 16, "target": 55}, {"source": 55, "target": 13}, {"source": 3, "target": 4, "label": "in"}, {"source": 9, "target": 3, "label": "attribution"}, {"source": 3, "target": 0, "label": "presupposition"}, {"source": 3, "target": 14, "label": "presupposition"}], "tops": [9], "framework": "drg", "time": "2025-04-11"}
{"id": "2", "input": "\"I wish I was playing for Real Madrid,\" the 21-year-old told Cadena Cope.", "nodes": [{"id": 0}, {"id": 1, "label": "\"now\""}, {"id": 2, "label": "time.n.08"}, {"id": 3, "label": "wish.v.01"}, {"id": 4, "label": "proposition.n.01"}, {"id": 5}, {"id": 6, "label": "play.v.01"}, {"id": 7, "label": "company.n.01"}, {"id": 8, "label": "\"real~madrid\""}, {"id": 9}, {"id": 10}, {"id": 11, "label": "proposition.n.01"}, {"id": 12, "label": "\"21\""}, {"id": 13, "label": "measure.n.02"}, {"id": 14, "label": "\"year\""}, {"id": 15, "label": "old.n.01"}, {"id": 16, "label": "time.n.08"}, {"id": 17, "label": "tell.v.02"}, {"id": 18, "label": "male.n.02"}, {"id": 19, "label": "\"cadena~cope\""}, {"id": 20}, {"id": 21}, {"id": 22, "label": "\"speaker\""}, {"id": 23, "label": "STIMULUS"}, {"id": 24, "label": "TPR"}, {"id": 25, "label": "NAME"}, {"id": 26, "label": "TIME"}, {"id": 27, "label": "CO-AGENT"}, {"id": 28, "label": "CO-AGENT"}, {"id": 29, "label": "TIME"}, {"id": 30, "label": "AGENT"}, {"id": 31, "label": "UNIT"}, {"id": 32, "label": "EQU"}, {"id": 33, "label": "STIMULUS"}, {"id": 34, "label": "NAME"}, {"id": 35, "label": "NAME"}, {"id": 36, "label": "EXPERIENCER"}, {"id": 37, "label": "AGENT"}, {"id": 38, "label": "TIME"}, {"id": 39, "label": "TIME"}, {"id": 40, "label": "TOPIC"}, {"id": 41, "label": "NAME"}, {"id": 42, "label": "QUANTITY"}, {"id": 43, "label": "RECIPIENT"}, {"id": 44, "label": "TIME"}], "edges": [{"source": 3, "target": 23}, {"source": 23, "target": 11}, {"source": 16, "target": 24}, {"source": 24, "target": 1}, {"source": 7, "target": 25}, {"source": 25, "target": 19}, {"source": 6, "target": 26}, {"source": 26, "target": 16}, {"source": 9, "target": 7, "label": "in"}, {"source": 6, "target": 27}, {"source": 27, "target": 7}, {"source": 6, "target": 28}, {"source": 28, "target": 18}, {"source": 3, "target": 29}, {"source": 29, "target": 2}, {"source": 6, "target": 30}, {"source": 30, "target": 22}, {"source": 13, "target": 31}, {"source": 31, "target": 14}, {"source": 2, "target": 32}, {"source": 32, "target": 1}, {"source": 3, "target": 33}, {"source": 33, "target": 4}, {"source": 18, "target": 34}, {"source": 34, "target": 8}, {"source": 7, "target": 35}, {"source": 35, "target": 8}, {"source": 3, "target": 36}, {"source": 36, "target": 22}, {"source": 17, "target": 37}, {"source": 37, "target": 22}, {"source": 17, "target": 38}, {"source": 38, "target": 16}, {"source": 5, "target": 11, "label": "in"}, {"source": 5, "target": 2, "label": "in"}, {"source": 3, "target": 39}, {"source": 39, "target": 16}, {"source": 17, "target": 40}, {"source": 40, "target": 11}, {"source": 5, "target": 16, "label": "in"}, {"source": 18, "target": 41}, {"source": 41, "target": 19}, {"source": 10, "target": 16, "label": "in"}, {"source": 0, "target": 6, "label": "in"}, {"source": 10, "target": 11, "label": "in"}, {"source": 20, "target": 7, "label": "in"}, {"source": 5, "target": 17, "label": "in"}, {"source": 10, "target": 17, "label": "in"}, {"source": 5, "target": 3, "label": "in"}, {"source": 21, "target": 10, "label": "presupposition"}, {"source": 10, "target": 2, "label": "in"}, {"source": 5, "target": 4, "label": "in"}, {"source": 10, "target": 3, "label": "in"}, {"source": 13, "target": 42}, {"source": 42, "target": 12}, {"source": 17, "target": 43}, {"source": 43, "target": 18}, {"source": 5, "target": 0, "label": "attribution"}, {"source": 10, "target": 4, "label": "in"}, {"source": 10, "target": 0, "label": "attribution"}, {"source": 20, "target": 10, "label": "presupposition"}, {"source": 9, "target": 0, "label": "presupposition"}, {"source": 17, "target": 44}, {"source": 44, "target": 2}, {"source": 10, "target": 5, "label": "attribution"}, {"source": 5, "target": 9, "label": "attribution"}, {"source": 20, "target": 18, "label": "in"}, {"source": 5, "target": 10, "label": "attribution"}, {"source": 10, "target": 9, "label": "attribution"}, {"source": 5, "target": 13, "label": "in"}], "tops": [10], "framework": "drg", "time": "2025-04-11"}
{"id": "3", "input": "\"Hopefully it could happen.", "nodes": [{"id": 0}, {"id": 1, "label": "proposition.n.01"}, {"id": 2}, {"id": 3, "label": "entity.n.01"}, {"id": 4}, {"id": 5, "label": "happen.v.01"}, {"id": 6}, {"id": 7, "label": "THEME"}], "edges": [{"source": 0, "target": 5, "label": "in"}, {"source": 5, "target": 7}, {"source": 7, "target": 3}, {"source": 6, "target": 3, "label": "in"}, {"source": 2, "target": 0, "label": "attribution"}, {"source": 6, "target": 0, "label": "presupposition"}, {"source": 4, "target": 0, "label": "possibility"}], "tops": [0], "framework": "drg", "time": "2025-04-11"}
{"id": "4", "input": "I love the way Madrid play.", "nodes": [{"id": 0}, {"id": 1, "label": "\"now\""}, {"id": 2, "label": "time.n.08"}, {"id": 3, "label": "love.v.01"}, {"id": 4, "label": "manner.n.01"}, {"id": 5, "label": "city.n.01"}, {"id": 6, "label": "\"madris\""}, {"id": 7, "label": "time.n.08"}, {"id": 8, "label": "play.v.01"}, {"id": 9}, {"id": 10, "label": "\"speaker\""}, {"id": 11, "label": "EXPERIENCER"}, {"id": 12, "label": "EQU"}, {"id": 13, "label": "EXPERIENCER"}, {"id": 14, "label": "AGENT"}, {"id": 15, "label": "MANNER"}, {"id": 16, "label": "TIME"}, {"id": 17, "label": "NAME"}, {"id": 18, "label": "EQU"}, {"id": 19, "label": "STIMULUS"}, {"id": 20, "label": "TIME"}, {"id": 21, "label": "TIME"}], "edges": [{"source": 3, "target": 11}, {"source": 11, "target": 5}, {"source": 0, "target": 2, "label": "in"}, {"source": 0, "target": 3, "label": "in"}, {"source": 0, "target": 4, "label": "in"}, {"source": 7, "target": 12}, {"source": 12, "target": 1}, {"source": 9, "target": 5, "label": "in"}, {"source": 0, "target": 7, "label": "in"}, {"source": 0, "target": 8, "label": "in"}, {"source": 9, "target": 0, "label": "presupposition"}, {"source": 3, "target": 13}, {"source": 13, "target": 10}, {"source": 8, "target": 14}, {"source": 14, "target": 5}, {"source": 8, "target": 15}, {"source": 15, "target": 4}, {"source": 3, "target": 16}, {"source": 16, "target": 2}, {"source": 5, "target": 17}, {"source": 17, "target": 6}, {"source": 2, "target": 18}, {"source": 18, "target": 1}, {"source": 3, "target": 19}, {"source": 19, "target": 4}, {"source": 8, "target": 20}, {"source": 20, "target": 7}, {"source": 8, "target": 21}, {"source": 21, "target": 2}], "tops": [0], "framework": "drg", "time": "2025-04-11"}
{"id": "5", "input": "I am not happy with the way things are.\"", "nodes": [{"id": 0}, {"id": 1, "label": "\"now\""}, {"id": 2, "label": "time.n.08"}, {"id": 3, "label": "happy.a.01"}, {"id": 4, "label": "way.n.01"}, {"id": 5, "label": "entity.n.01"}, {"id": 6, "label": "be.v.03"}, {"id": 7}, {"id": 8, "label": "\"speaker\""}, {"id": 9}, {"id": 10, "label": "TIME"}, {"id": 11, "label": "TIME"}, {"id": 12, "label": "MANNER"}, {"id": 13, "label": "EQU"}, {"id": 14, "label": "EXPERIENCER"}, {"id": 15, "label": "THEME"}, {"id": 16, "label": "STIMULUS"}, {"id": 17, "label": "STIMULUS"}], "edges": [{"source": 6, "target": 10}, {"source": 10, "target": 2}, {"source": 3, "target": 11}, {"source": 11, "target": 2}, {"source": 6, "target": 12}, {"source": 12, "target": 4}, {"source": 0, "target": 3, "label": "in"}, {"source": 2, "target": 13}, {"source": 13, "target": 1}, {"source": 7, "target": 2, "label": "in"}, {"source": 7, "target": 0, "label": "negation"}, {"source": 3, "target": 14}, {"source": 14, "target": 8}, {"source": 9, "target": 0, "label": "presupposition"}, {"source": 6, "target": 15}, {"source": 15, "target": 5}, {"source": 9, "target": 5, "label": "in"}, {"source": 0, "target": 6, "label": "in"}, {"source": 0, "target": 4, "label": "in"}, {"source": 9, "target": 4, "label": "in"}, {"source": 9, "target": 2, "label": "in"}, {"source": 3, "target": 16}, {"source": 16, "target": 4}, {"source": 3, "target": 17}, {"source": 17, "target": 5}], "tops": [7], "framework": "drg", "time": "2025-04-11"}
{"id": "6", "input": "The striker joined the Gunners from Seville for £17m at the start of 2004, but it has frequently been reported that he is homesick.", "nodes": [{"id": 0}, {"id": 1, "label": "\"now\""}, {"id": 2, "label": "person.n.01"}, {"id": 3, "label": "striker.n.01"}, {"id": 4, "label": "time.n.08"}, {"id": 5, "label": "join.v.02"}, {"id": 6, "label": "person.n.01"}, {"id": 7}, {"id": 8, "label": "gunner.n.01"}, {"id": 9}, {"id": 10, "label": "island.n.01"}, {"id": 11, "label": "\"seville\""}, {"id": 12, "label": "measure.n.02"}, {"id": 13, "label": "\"dollar\""}, {"id": 14, "label": "\"17\""}, {"id": 15, "label": "start.v.02"}, {"id": 16, "label": "\"2004\""}, {"id": 17}, {"id": 18, "label": "time.n.08"}, {"id": 19, "label": "frequently.a.01"}, {"id": 20, "label": "report.v.01"}, {"id": 21, "label": "proposition.n.01"}, {"id": 22}, {"id": 23, "label": "homesick.a.01"}, {"id": 24}, {"id": 25, "label": "male.n.02"}, {"id": 26, "label": "YEAROFCENTURY"}, {"id": 27, "label": "TPR"}, {"id": 28, "label": "ROLE"}, {"id": 29, "label": "ROLE"}, {"id": 30, "label": "UNIT"}, {"id": 31, "label": "QUANTITY"}, {"id": 32, "label": "ATTRIBUTE"}, {"id": 33, "label": "THEME"}, {"id": 34, "label": "THEME"}, {"id": 35, "label": "TOPIC"}, {"id": 36, "label": "YEAROFCENTURY"}, {"id": 37, "label": "AGENT"}, {"id": 38, "label": "ATTRIBUTE"}, {"id": 39, "label": "ROLE"}, {"id": 40, "label": "TIME"}, {"id": 41, "label": "TPR"}, {"id": 42, "label": "AGENT"}, {"id": 43, "label": "AGENT"}, {"id": 44, "label": "LOCATION"}, {"id": 45, "label": "NAME"}, {"id": 46, "label": "TIME"}, {"id": 47, "label": "TIME"}, {"id": 48, "label": "TIME"}, {"id": 49, "label": "TIME"}], "edges": [{"source": 18, "target": 26}, {"source": 26, "target": 16}, {"source": 4, "target": 27}, {"source": 27, "target": 1}, {"source": 7, "target": 8, "label": "in"}, {"source": 24, "target": 25, "label": "in"}, {"source": 7, "target": 6, "label": "in"}, {"source": 2, "target": 28}, {"source": 28, "target": 3}, {"source": 25, "target": 29}, {"source": 29, "target": 3}, {"source": 12, "target": 30}, {"source": 30, "target": 13}, {"source": 12, "target": 31}, {"source": 31, "target": 14}, {"source": 22, "target": 20, "label": "in"}, {"source": 25, "target": 32}, {"source": 32, "target": 23}, {"source": 5, "target": 33}, {"source": 33, "target": 25}, {"source": 5, "target": 34}, {"source": 34, "target": 6}, {"source": 20, "target": 35}, {"source": 35, "target": 21}, {"source": 4, "target": 36}, {"source": 36, "target": 16}, {"source": 5, "target": 37}, {"source": 37, "target": 2}, {"source": 6, "target": 38}, {"source": 38, "target": 23}, {"source": 6, "target": 39}, {"source": 39, "target": 8}, {"source": 24, "target": 3, "label": "in"}, {"source": 5, "target": 40}, {"source": 40, "target": 4}, {"source": 22, "target": 21, "label": "in"}, {"source": 18, "target": 41}, {"source": 41, "target": 1}, {"source": 0, "target": 23, "label": "in"}, {"source": 20, "target": 42}, {"source": 42, "target": 2}, {"source": 22, "target": 4, "label": "in"}, {"source": 20, "target": 43}, {"source": 43, "target": 25}, {"source": 7, "target": 0, "label": "presupposition"}, {"source": 5, "target": 44}, {"source": 44, "target": 10}, {"source": 22, "target": 2, "label": "in"}, {"source": 22, "target": 0, "label": "attribution"}, {"source": 17, "target": 4, "label": "in"}, {"source": 24, "target": 0, "label": "presupposition"}, {"source": 9, "target": 0, "label": "presupposition"}, {"source": 0, "target": 12, "label": "in"}, {"source": 10, "target": 45}, {"source": 45, "target": 11}, {"source": 17, "target": 5, "label": "in"}, {"source": 23, "target": 46}, {"source": 46, "target": 4}, {"source": 24, "target": 17, "label": "presupposition"}, {"source": 0, "target": 5, "label": "in"}, {"source": 20, "target": 47}, {"source": 47, "target": 4}, {"source": 24, "target": 2, "label": "in"}, {"source": 17, "target": 0, "label": "presupposition"}, {"source": 9, "target": 17, "label": "presupposition"}, {"source": 7, "target": 17, "label": "presupposition"}, {"source": 22, "target": 19, "label": "in"}, {"source": 24, "target": 22, "label": "presupposition"}, {"source": 22, "target": 18, "label": "in"}, {"source": 23, "target": 48}, {"source": 48, "target": 18}, {"source": 5, "target": 49}, {"source": 49, "target": 18}], "tops": [22], "framework": "drg", "time": "2025-04-11"}
{"id": "7", "input": "He began the season in superb form but has struggled to maintain his high standards as Arsenal have gradually lost the Premiership initiative to Manchester United and Chelsea.", "nodes": [{"id": 0}, {"id": 1, "label": "\"now\""}, {"id": 2, "label": "time.n.08"}, {"id": 3, "label": "begin.v.02"}, {"id": 4}, {"id": 5, "label": "season.n.01"}, {"id": 6, "label": "superb.a.01"}, {"id": 7, "label": "form.n.01"}, {"id": 8}, {"id": 9, "label": "struggle.v.01"}, {"id": 10}, {"id": 11, "label": "proposition.n.01"}, {"id": 12, "label": "maintain.v.02"}, {"id": 13, "label": "high.a.01"}, {"id": 14}, {"id": 15, "label": "standard.n.01"}, {"id": 16}, {"id": 17, "label": "team.n.01"}, {"id": 18, "label": "\"arsenal\""}, {"id": 19, "label": "time.n.08"}, {"id": 20, "label": "gradually.r.01"}, {"id": 21, "label": "lose.v.01"}, {"id": 22, "label": "premiership.n.01"}, {"id": 23, "label": "\"premiership~initiative\""}, {"id": 24, "label": "initiative.n.01"}, {"id": 25, "label": "\"manchester~united\""}, {"id": 26, "label": "team.n.01"}, {"id": 27, "label": "entity.n.01"}, {"id": 28}, {"id": 29, "label": "team.n.01"}, {"id": 30, "label": "\"chelsea\""}, {"id": 31}, {"id": 32, "label": "male.n.02"}, {"id": 33, "label": "AGENT"}, {"id": 34, "label": "THEME"}, {"id": 35, "label": "TIME"}, {"id": 36, "label": "AGENT"}, {"id": 37, "label": "AGENT"}, {"id": 38, "label": "AGENT"}, {"id": 39, "label": "AGENT"}, {"id": 40, "label": "TPR"}, {"id": 41, "label": "SUB"}, {"id": 42, "label": "TPR"}, {"id": 43, "label": "DESTINATION"}, {"id": 44, "label": "EXPERIENCER"}, {"id": 45, "label": "THEME"}, {"id": 46, "label": "NAME"}, {"id": 47, "label": "THEME"}, {"id": 48, "label": "AGENT"}, {"id": 49, "label": "THEME"}, {"id": 50, "label": "THEME"}, {"id": 51, "label": "TIME"}, {"id": 52, "label": "AGENT"}, {"id": 53, "label": "THEME"}, {"id": 54, "label": "MANNER"}, {"id": 55, "label": "AGENT"}, {"id": 56, "label": "TIME"}, {"id": 57, "label": "ATTRIBUTE"}, {"id": 58, "label": "MANNER"}, {"id": 59, "label": "SUB"}, {"id": 60, "label": "NAME"}, {"id": 61, "label": "AGENT"}, {"id": 62, "label": "NAME"}], "edges": [{"source": 3, "target": 33}, {"source": 33, "target": 32}, {"source": 3, "target": 34}, {"source": 34, "target": 5}, {"source": 3, "target": 35}, {"source": 35, "target": 2}, {"source": 12, "target": 36}, {"source": 36, "target": 32}, {"source": 21, "target": 37}, {"source": 37, "target": 27}, {"source": 21, "target": 38}, {"source": 38, "target": 32}, {"source": 9, "target": 39}, {"source": 39, "target": 32}, {"source": 19, "target": 40}, {"source": 40, "target": 1}, {"source": 27, "target": 41}, {"source": 41, "target": 32}, {"source": 31, "target": 32, "label": "in"}, {"source": 2, "target": 42}, {"source": 42, "target": 1}, {"source": 3, "target": 43}, {"source": 43, "target": 7}, {"source": 15, "target": 44}, {"source": 44, "target": 32}, {"source": 0, "target": 12, "label": "in"}, {"source": 0, "target": 21, "label": "in"}, {"source": 0, "target": 27, "label": "in"}, {"source": 21, "target": 45}, {"source": 45, "target": 15}, {"source": 0, "target": 20, "label": "in"}, {"source": 10, "target": 0, "label": "attribution"}, {"source": 29, "target": 46}, {"source": 46, "target": 30}, {"source": 12, "target": 47}, {"source": 47, "target": 15}, {"source": 3, "target": 48}, {"source": 48, "target": 26}, {"source": 21, "target": 49}, {"source": 49, "target": 24}, {"source": 3, "target": 50}, {"source": 50, "target": 24}, {"source": 21, "target": 51}, {"source": 51, "target": 19}, {"source": 3, "target": 52}, {"source": 52, "target": 17}, {"source": 28, "target": 0, "label": "presupposition"}, {"source": 4, "target": 10, "label": "presupposition"}, {"source": 9, "target": 53}, {"source": 53, "target": 11}, {"source": 10, "target": 2, "label": "in"}, {"source": 21, "target": 54}, {"source": 54, "target": 20}, {"source": 10, "target": 9, "label": "in"}, {"source": 31, "target": 14, "label": "presupposition"}, {"source": 12, "target": 55}, {"source": 55, "target": 27}, {"source": 31, "target": 10, "label": "presupposition"}, {"source": 10, "target": 3, "label": "in"}, {"source": 3, "target": 56}, {"source": 56, "target": 19}, {"source": 10, "target": 11, "label": "in"}, {"source": 28, "target": 29, "label": "in"}, {"source": 15, "target": 57}, {"source": 57, "target": 13}, {"source": 3, "target": 58}, {"source": 58, "target": 20}, {"source": 27, "target": 59}, {"source": 59, "target": 29}, {"source": 29, "target": 60}, {"source": 60, "target": 23}, {"source": 4, "target": 5, "label": "in"}, {"source": 4, "target": 8, "label": "presupposition"}, {"source": 8, "target": 0, "label": "presupposition"}, {"source": 8, "target": 7, "label": "in"}, {"source": 10, "target": 7, "label": "in"}, {"source": 16, "target": 10, "label": "presupposition"}, {"source": 16, "target": 8, "label": "presupposition"}, {"source": 28, "target": 8, "label": "presupposition"}, {"source": 10, "target": 19, "label": "in"}, {"source": 21, "target": 61}, {"source": 61, "target": 17}, {"source": 14, "target": 0, "label": "presupposition"}, {"source": 26, "target": 62}, {"source": 62, "target": 18}, {"source": 14, "target": 15, "label": "in"}, {"source": 14, "target": 27, "label": "in"}], "tops": [10], "framework": "drg", "time": "2025-04-11"}
{"id": "8", "input": "\"If I am not (playing for Real) I am going to have to carry on playing with some bad people,\" he added.", "nodes": [{"id": 0}, {"id": 1}, {"id": 2, "label": "time.n.08"}, {"id": 3}, {"id": 4, "label": "play.v.01"}, {"id": 5, "label": "male.n.02"}, {"id": 6, "label": "carry.v.04"}, {"id": 7, "label": "play.v.01"}, {"id": 8, "label": "bad.a.02"}, {"id": 9, "label": "person.n.01"}, {"id": 10}, {"id": 11, "label": "proposition.n.01"}, {"id": 12, "label": "time.n.08"}, {"id": 13, "label": "add.v.01"}, {"id": 14}, {"id": 15, "label": "\"speaker\""}, {"id": 16, "label": "TIME"}, {"id": 17, "label": "AGENT"}, {"id": 18, "label": "TOPIC"}, {"id": 19, "label": "AGENT"}, {"id": 20, "label": "AGENT"}, {"id": 21, "label": "CO-AGENT"}, {"id": 22, "label": "AGENT"}, {"id": 23, "label": "TIME"}, {"id": 24, "label": "AGENT"}, {"id": 25, "label": "AGENT"}, {"id": 26, "label": "AGENT"}], "edges": [{"source": 13, "target": 16}, {"source": 16, "target": 12}, {"source": 7, "target": 17}, {"source": 17, "target": 15}, {"source": 14, "target": 10, "label": "presupposition"}, {"source": 13, "target": 18}, {"source": 18, "target": 11}, {"source": 4, "target": 19}, {"source": 19, "target": 15}, {"source": 6, "target": 20}, {"source": 20, "target": 15}, {"source": 10, "target": 11, "label": "in"}, {"source": 10, "target": 12, "label": "in"}, {"source": 0, "target": 9, "label": "in"}, {"source": 7, "target": 21}, {"source": 21, "target": 9}, {"source": 13, "target": 22}, {"source": 22, "target": 15}, {"source": 4, "target": 23}, {"source": 23, "target": 2}, {"source": 4, "target": 24}, {"source": 24, "target": 9}, {"source": 4, "target": 25}, {"source": 25, "target": 5}, {"source": 7, "target": 26}, {"source": 26, "target": 5}, {"source": 10, "target": 13, "label": "in"}, {"source": 1, "target": 9, "label": "in"}, {"source": 10, "target": 3, "label": "attribution"}, {"source": 0, "target": 8, "label": "in"}], "tops": [10], "framework": "drg", "time": "2025-04-11"}
{"id": "9", "input": "\"I am sure there are none in the Real dressing room.", "nodes": [{"id": 0}, {"id": 1, "label": "\"now\""}, {"id": 2, "label": "time.n.08"}, {"id": 3, "label": "sure.a.02"}, {"id": 4, "label": "proposition.n.01"}, {"id": 5, "label": "time.n.08"}, {"id": 6, "label": "be.v.03"}, {"id": 7, "label": "person.n.01"}, {"id": 8, "label": "entity.n.01"}, {"id": 9, "label": "dressing_room.n.01"}, {"id": 10}, {"id": 11}, {"id": 12, "label": "\"speaker\""}, {"id": 13, "label": "THEME"}, {"id": 14, "label": "TIME"}, {"id": 15, "label": "TIME"}, {"id": 16, "label": "EXPERIENCER"}, {"id": 17, "label": "STIMULUS"}, {"id": 18, "label": "LOCATION"}, {"id": 19, "label": "EQU"}, {"id": 20, "label": "EQU"}, {"id": 21, "label": "THEME"}, {"id": 22, "label": "TIME"}], "edges": [{"source": 6, "target": 13}, {"source": 13, "target": 7}, {"source": 11, "target": 5, "label": "in"}, {"source": 0, "target": 6, "label": "in"}, {"source": 0, "target": 7, "label": "in"}, {"source": 0, "target": 8, "label": "in"}, {"source": 3, "target": 14}, {"source": 14, "target": 2}, {"source": 6, "target": 15}, {"source": 15, "target": 5}, {"source": 3, "target": 16}, {"source": 16, "target": 12}, {"source": 11, "target": 2, "label": "in"}, {"source": 3, "target": 17}, {"source": 17, "target": 4}, {"source": 6, "target": 18}, {"source": 18, "target": 9}, {"source": 10, "target": 9, "label": "in"}, {"source": 2, "target": 19}, {"source": 19, "target": 1}, {"source": 5, "target": 20}, {"source": 20, "target": 1}, {"source": 6, "target": 21}, {"source": 21, "target": 8}, {"source": 11, "target": 0, "label": "negation"}, {"source": 0, "target": 5, "label": "in"}, {"source": 11, "target": 3, "label": "in"}, {"source": 0, "target": 2, "label": "in"}, {"source": 11, "target": 4, "label": "in"}, {"source": 10, "target": 0, "label": "presupposition"}, {"source": 6, "target": 22}, {"source": 22, "target": 2}], "tops": [11], "framework": "drg", "time": "2025-04-11"}
{"id": "10", "input": "\"I am happy Madrid is interested in me because it has always been my dream since I was little to play there.\"", "nodes": [{"id": 0}, {"id": 1, "label": "\"now\""}, {"id": 2, "label": "time.n.08"}, {"id": 3, "label": "happy.a.01"}, {"id": 4, "label": "proposition.n.01"}, {"id": 5}, {"id": 6, "label": "city.n.01"}, {"id": 7, "label": "\"madrid\""}, {"id": 8, "label": "time.n.08"}, {"id": 9, "label": "interested.a.02"}, {"id": 10, "label": "time.n.08"}, {"id": 11}, {"id": 12}, {"id": 13, "label": "be.v.02"}, {"id": 14, "label": "dream.n.01"}, {"id": 15, "label": "old.a.01"}, {"id": 16, "label": "score.n.03"}, {"id": 17}, {"id": 18, "label": "play.v.01"}, {"id": 19}, {"id": 20, "label": "\"speaker\""}, {"id": 21}, {"id": 22, "label": "EXPERIENCER"}, {"id": 23, "label": "EXPERIENCER"}, {"id": 24, "label": "AGENT"}, {"id": 25, "label": "TPR"}, {"id": 26, "label": "EXPERIENCER"}, {"id": 27, "label": "EQU"}, {"id": 28, "label": "NAME"}, {"id": 29, "label": "EQU"}, {"id": 30, "label": "TIME"}, {"id": 31, "label": "STIMULUS"}, {"id": 32, "label": "EXPERIENCER"}, {"id": 33, "label": "TIME"}, {"id": 34, "label": "TIME"}, {"id": 35, "label": "TIME"}, {"id": 36, "label": "TIME"}, {"id": 37, "label": "TIME"}, {"id": 38, "label": "AGENT"}, {"id": 39, "label": "THEME"}, {"id": 40, "label": "TIME"}, {"id": 41, "label": "CO-THEME"}, {"id": 42, "label": "STIMULUS"}, {"id": 43, "label": "TIME"}], "edges": [{"source": 9, "target": 22}, {"source": 22, "target": 6}, {"source": 14, "target": 23}, {"source": 23, "target": 20}, {"source": 18, "target": 24}, {"source": 24, "target": 20}, {"source": 10, "target": 25}, {"source": 25, "target": 1}, {"source": 19, "target": 6, "label": "in"}, {"source": 3, "target": 26}, {"source": 26, "target": 20}, {"source": 8, "target": 27}, {"source": 27, "target": 1}, {"source": 6, "target": 28}, {"source": 28, "target": 7}, {"source": 2, "target": 29}, {"source": 29, "target": 1}, {"source": 3, "target": 30}, {"source": 30, "target": 2}, {"source": 3, "target": 31}, {"source": 31, "target": 4}, {"source": 9, "target": 32}, {"source": 32, "target": 20}, {"source": 9, "target": 33}, {"source": 33, "target": 8}, {"source": 5, "target": 0, "label": "attribution"}, {"source": 13, "target": 34}, {"source": 34, "target": 8}, {"source": 13, "target": 35}, {"source": 35, "target": 10}, {"source": 9, "target": 36}, {"source": 36, "target": 2}, {"source": 11, "target": 12, "label": "condition"}, {"source": 12, "target": 8, "label": "in"}, {"source": 12, "target": 0, "label": "consequence"}, {"source": 5, "target": 2, "label": "in"}, {"source": 18, "target": 37}, {"source": 37, "target": 10}, {"source": 0, "target": 9, "label": "in"}, {"source": 18, "target": 38}, {"source": 38, "target": 6}, {"source": 5, "target": 3, "label": "in"}, {"source": 18, "target": 39}, {"source": 39, "target": 14}, {"source": 17, "target": 2, "label": "in"}, {"source": 19, "target": 0, "label": "presupposition"}, {"source": 21, "target": 0, "label": "presupposition"}, {"source": 17, "target": 3, "label": "in"}, {"source": 9, "target": 40}, {"source": 40, "target": 10}, {"source": 5, "target": 17, "label": "presupposition"}, {"source": 13, "target": 41}, {"source": 41, "target": 14}, {"source": 5, "target": 8, "label": "in"}, {"source": 5, "target": 4, "label": "in"}, {"source": 19, "target": 17, "label": "presupposition"}, {"source": 9, "target": 42}, {"source": 42, "target": 14}, {"source": 17, "target": 4, "label": "in"}, {"source": 0, "target": 15, "label": "in"}, {"source": 15, "target": 43}, {"source": 43, "target": 8}, {"source": 0, "target": 2, "label": "in"}, {"source": 5, "target": 12, "label": "attribution"}, {"source": 12, "target": 17, "label": "consequence"}, {"source": 5, "target": 21, "label": "attribution"}, {"source": 17, "target": 12, "label": "attribution"}], "tops": [0], "framework": "drg", "time": "2025-04-11"}
{"id": "11", "input": "Before the story surfaced, Reyes had moved to play down reports linking him with the Spanish giants, issuing a statement through Arsenal describing the speculation as \"flattering\".", "nodes": [{"id": 0}, {"id": 1, "label": "\"now\""}, {"id": 2, "label": "story.n.01"}, {"id": 3, "label": "time.n.08"}, {"id": 4, "label": "surface.v.01"}, {"id": 5}, {"id": 6, "label": "\"reyes\""}, {"id": 7, "label": "time.n.08"}, {"id": 8, "label": "move.v.01"}, {"id": 9}, {"id": 10, "label": "proposition.n.01"}, {"id": 11, "label": "play.v.07"}, {"id": 12, "label": "report.n.01"}, {"id": 13, "label": "link.v.01"}, {"id": 14, "label": "country.n.02"}, {"id": 15, "label": "\"spain\""}, {"id": 16, "label": "person.n.01"}, {"id": 17}, {"id": 18, "label": "giant.n.01"}, {"id": 19}, {"id": 20, "label": "issu.v.01"}, {"id": 21, "label": "statement.n.01"}, {"id": 22}, {"id": 23, "label": "male.n.02"}, {"id": 24, "label": "\"arsenal\""}, {"id": 25, "label": "describ.v.01"}, {"id": 26}, {"id": 27, "label": "speculation.n.01"}, {"id": 28, "label": "flattering.a.01"}, {"id": 29}, {"id": 30, "label": "male.n.02"}, {"id": 31, "label": "AGENT"}, {"id": 32, "label": "THEME"}, {"id": 33, "label": "TPR"}, {"id": 34, "label": "THEME"}, {"id": 35, "label": "AGENT"}, {"id": 36, "label": "NAME"}, {"id": 37, "label": "NAME"}, {"id": 38, "label": "TPR"}, {"id": 39, "label": "TIME"}, {"id": 40, "label": "THEME"}, {"id": 41, "label": "THEME"}, {"id": 42, "label": "THEME"}, {"id": 43, "label": "NAME"}, {"id": 44, "label": "NAME"}, {"id": 45, "label": "THEME"}, {"id": 46, "label": "THEME"}, {"id": 47, "label": "TIME"}, {"id": 48, "label": "THEME"}], "edges": [{"source": 29, "target": 30, "label": "in"}, {"source": 11, "target": 31}, {"source": 31, "target": 30}, {"source": 0, "target": 28, "label": "in"}, {"source": 4, "target": 32}, {"source": 32, "target": 30}, {"source": 3, "target": 33}, {"source": 33, "target": 1}, {"source": 4, "target": 34}, {"source": 34, "target": 21}, {"source": 26, "target": 27, "label": "in"}, {"source": 20, "target": 35}, {"source": 35, "target": 30}, {"source": 30, "target": 36}, {"source": 36, "target": 6}, {"source": 14, "target": 37}, {"source": 37, "target": 15}, {"source": 7, "target": 38}, {"source": 38, "target": 1}, {"source": 4, "target": 39}, {"source": 39, "target": 3}, {"source": 4, "target": 40}, {"source": 40, "target": 2}, {"source": 11, "target": 41}, {"source": 41, "target": 27}, {"source": 13, "target": 42}, {"source": 42, "target": 27}, {"source": 23, "target": 43}, {"source": 43, "target": 24}, {"source": 0, "target": 11, "label": "in"}, {"source": 26, "target": 0, "label": "presupposition"}, {"source": 23, "target": 44}, {"source": 44, "target": 15}, {"source": 25, "target": 45}, {"source": 45, "target": 27}, {"source": 5, "target": 3, "label": "in"}, {"source": 0, "target": 12, "label": "in"}, {"source": 9, "target": 0, "label": "attribution"}, {"source": 5, "target": 0, "label": "presupposition"}, {"source": 13, "target": 46}, {"source": 46, "target": 30}, {"source": 17, "target": 0, "label": "presupposition"}, {"source": 5, "target": 21, "label": "in"}, {"source": 4, "target": 47}, {"source": 47, "target": 7}, {"source": 22, "target": 5, "label": "presupposition"}, {"source": 22, "target": 23, "label": "in"}, {"source": 0, "target": 13, "label": "in"}, {"source": 5, "target": 9, "label": "continuation"}, {"source": 22, "target": 9, "label": "presupposition"}, {"source": 9, "target": 3, "label": "in"}, {"source": 5, "target": 7, "label": "in"}, {"source": 25, "target": 48}, {"source": 48, "target": 2}], "tops": [5], "framework": "drg", "time": "2025-04-11"}
{"id": "12", "input": "\"I have seen the stories in the media linking me with Real Madrid,\" he had said on Thursday lunchtime.", "nodes": [{"id": 0}, {"id": 1, "label": "\"now\""}, {"id": 2, "label": "time.n.08"}, {"id": 3, "label": "see.v.01"}, {"id": 4, "label": "storie.n.03"}, {"id": 5, "label": "media.n.01"}, {"id": 6, "label": "link.v.04"}, {"id": 7, "label": "male.n.02"}, {"id": 8, "label": "team.n.01"}, {"id": 9, "label": "\"real~madrid\""}, {"id": 10}, {"id": 11, "label": "proposition.n.01"}, {"id": 12, "label": "proposition.n.01"}, {"id": 13, "label": "male.n.02"}, {"id": 14, "label": "time.n.08"}, {"id": 15, "label": "say.v.01"}, {"id": 16, "label": "\"thursday\""}, {"id": 17, "label": "lunchtime.n.01"}, {"id": 18}, {"id": 19, "label": "\"speaker\""}, {"id": 20, "label": "EXPERIENCER"}, {"id": 21, "label": "TPR"}, {"id": 22, "label": "TOPIC"}, {"id": 23, "label": "STIMULUS"}, {"id": 24, "label": "TPR"}, {"id": 25, "label": "DAYOFWEEK"}, {"id": 26, "label": "DAYOFWEEK"}, {"id": 27, "label": "NAME"}, {"id": 28, "label": "THEME"}, {"id": 29, "label": "TOPIC"}, {"id": 30, "label": "AGENT"}, {"id": 31, "label": "AGENT"}, {"id": 32, "label": "EXPERIENCER"}, {"id": 33, "label": "EQU"}, {"id": 34, "label": "TIME"}, {"id": 35, "label": "LOCATION"}, {"id": 36, "label": "TIME"}, {"id": 37, "label": "TIME"}, {"id": 38, "label": "TIME"}, {"id": 39, "label": "EQU"}], "edges": [{"source": 3, "target": 20}, {"source": 20, "target": 19}, {"source": 2, "target": 21}, {"source": 21, "target": 1}, {"source": 15, "target": 22}, {"source": 22, "target": 12}, {"source": 3, "target": 23}, {"source": 23, "target": 4}, {"source": 14, "target": 24}, {"source": 24, "target": 1}, {"source": 14, "target": 25}, {"source": 25, "target": 16}, {"source": 10, "target": 12, "label": "in"}, {"source": 18, "target": 10, "label": "presupposition"}, {"source": 2, "target": 26}, {"source": 26, "target": 16}, {"source": 18, "target": 7, "label": "in"}, {"source": 8, "target": 27}, {"source": 27, "target": 9}, {"source": 6, "target": 28}, {"source": 28, "target": 8}, {"source": 18, "target": 13, "label": "in"}, {"source": 10, "target": 11, "label": "in"}, {"source": 0, "target": 4, "label": "in"}, {"source": 15, "target": 29}, {"source": 29, "target": 11}, {"source": 10, "target": 15, "label": "in"}, {"source": 15, "target": 30}, {"source": 30, "target": 7}, {"source": 15, "target": 31}, {"source": 31, "target": 13}, {"source": 3, "target": 32}, {"source": 32, "target": 7}, {"source": 2, "target": 33}, {"source": 33, "target": 17}, {"source": 3, "target": 34}, {"source": 34, "target": 2}, {"source": 0, "target": 3, "label": "in"}, {"source": 4, "target": 35}, {"source": 35, "target": 5}, {"source": 10, "target": 0, "label": "attribution"}, {"source": 3, "target": 36}, {"source": 36, "target": 14}, {"source": 6, "target": 37}, {"source": 37, "target": 2}, {"source": 0, "target": 6, "label": "in"}, {"source": 0, "target": 2, "label": "in"}, {"source": 6, "target": 38}, {"source": 38, "target": 14}, {"source": 14, "target": 39}, {"source": 39, "target": 17}], "tops": [10], "framework": "drg", "time": "2025-04-11"}
{"id": "13", "input": "\"But not only am I under contract at Arsenal, I am happy here and committed to helping the team win more trophies.\"", "nodes": [{"id": 0}, {"id": 1, "label": "\"now\""}, {"id": 2}, {"id": 3}, {"id": 4, "label": "time.n.08"}, {"id": 5, "label": "contract.n.01"}, {"id": 6, "label": "team.n.01"}, {"id": 7, "label": "\"arsenal\""}, {"id": 8}, {"id": 9, "label": "time.n.08"}, {"id": 10, "label": "happy.a.01"}, {"id": 11}, {"id": 12, "label": "committed.a.01"}, {"id": 13, "label": "help.v.01"}, {"id": 14}, {"id": 15, "label": "team.n.01"}, {"id": 16, "label": "win.v.01"}, {"id": 17, "label": "trophy.n.01"}, {"id": 18}, {"id": 19, "label": "\"speaker\""}, {"id": 20}, {"id": 21, "label": "EQU"}, {"id": 22, "label": "AGENT"}, {"id": 23, "label": "EXPERIENCER"}, {"id": 24, "label": "EQU"}, {"id": 25, "label": "THEME"}, {"id": 26, "label": "AGENT"}, {"id": 27, "label": "AGENT"}, {"id": 28, "label": "AGENT"}, {"id": 29, "label": "NAME"}, {"id": 30, "label": "AGENT"}, {"id": 31, "label": "TIME"}, {"id": 32, "label": "AGENT"}, {"id": 33, "label": "AGENT"}], "edges": [{"source": 4, "target": 21}, {"source": 21, "target": 1}, {"source": 16, "target": 22}, {"source": 22, "target": 19}, {"source": 10, "target": 23}, {"source": 23, "target": 19}, {"source": 9, "target": 24}, {"source": 24, "target": 1}, {"source": 16, "target": 25}, {"source": 25, "target": 17}, {"source": 13, "target": 26}, {"source": 26, "target": 19}, {"source": 12, "target": 27}, {"source": 27, "target": 19}, {"source": 16, "target": 28}, {"source": 28, "target": 15}, {"source": 6, "target": 29}, {"source": 29, "target": 7}, {"source": 13, "target": 30}, {"source": 30, "target": 15}, {"source": 0, "target": 4, "label": "in"}, {"source": 14, "target": 15, "label": "in"}, {"source": 18, "target": 8, "label": "presupposition"}, {"source": 20, "target": 0, "label": "presupposition"}, {"source": 10, "target": 31}, {"source": 31, "target": 4}, {"source": 0, "target": 10, "label": "in"}, {"source": 14, "target": 8, "label": "presupposition"}, {"source": 18, "target": 0, "label": "presupposition"}, {"source": 0, "target": 9, "label": "in"}, {"source": 0, "target": 2, "label": "continuation"}, {"source": 0, "target": 16, "label": "in"}, {"source": 20, "target": 11, "label": "continuation"}, {"source": 20, "target": 15, "label": "in"}, {"source": 13, "target": 32}, {"source": 32, "target": 6}, {"source": 16, "target": 33}, {"source": 33, "target": 6}, {"source": 0, "target": 5, "label": "in"}, {"source": 8, "target": 2, "label": "continuation"}], "tops": [0], "framework": "drg", "time": "2025-04-11"}
{"id": "14", "input": "Butragueno, meanwhile, was angry at being impersonated by the radio disc jockey.", "nodes": [{"id": 0}, {"id": 1, "label": "\"now\""}, {"id": 2, "label": "\"butragueno\""}, {"id": 3, "label": "time.n.08"}, {"id": 4, "label": "angry.a.01"}, {"id": 5, "label": "impersonate.v.04"}, {"id": 6, "label": "radio.n.01"}, {"id": 7}, {"id": 8}, {"id": 9, "label": "male.n.02"}, {"id": 10, "label": "EXPERIENCER"}, {"id": 11, "label": "TIME"}, {"id": 12, "label": "NAME"}, {"id": 13, "label": "THEME"}, {"id": 14, "label": "TPR"}, {"id": 15, "label": "TIME"}], "edges": [{"source": 8, "target": 9, "label": "in"}, {"source": 0, "target": 3, "label": "in"}, {"source": 0, "target": 4, "label": "in"}, {"source": 0, "target": 5, "label": "in"}, {"source": 4, "target": 10}, {"source": 10, "target": 9}, {"source": 8, "target": 0, "label": "presupposition"}, {"source": 4, "target": 11}, {"source": 11, "target": 3}, {"source": 9, "target": 12}, {"source": 12, "target": 2}, {"source": 5, "target": 13}, {"source": 13, "target": 9}, {"source": 3, "target": 14}, {"source": 14, "target": 1}, {"source": 5, "target": 15}, {"source": 15, "target": 3}, {"source": 7, "target": 0, "label": "presupposition"}, {"source": 7, "target": 6, "label": "in"}], "tops": [0], "framework": "drg", "time": "2025-04-11"}
{"id": "15", "input": "\"It is a disgrace, there is no foundation to this,\" he said.", "nodes": [{"id": 0}, {"id": 1}, {"id": 2, "label": "\"now\""}, {"id": 3, "label": "time.n.08"}, {"id": 4, "label": "be.v.01"}, {"id": 5, "label": "disgrace.n.01"}, {"id": 6}, {"id": 7, "label": "be.v.03"}, {"id": 8}, {"id": 9, "label": "foundation.n.01"}, {"id": 10, "label": "entity.n.01"}, {"id": 11}, {"id": 12, "label": "proposition.n.01"}, {"id": 13, "label": "proposition.n.01"}, {"id": 14, "label": "time.n.08"}, {"id": 15, "label": "say.v.01"}, {"id": 16}, {"id": 17, "label": "male.n.02"}, {"id": 18, "label": "TIME"}, {"id": 19, "label": "TIME"}, {"id": 20, "label": "THEME"}, {"id": 21, "label": "AGENT"}, {"id": 22, "label": "TPR"}, {"id": 23, "label": "TOPIC"}, {"id": 24, "label": "EQU"}, {"id": 25, "label": "THEME"}, {"id": 26, "label": "TOPIC"}, {"id": 27, "label": "THEME"}, {"id": 28, "label": "TIME"}, {"id": 29, "label": "CO-THEME"}, {"id": 30, "label": "TIME"}, {"id": 31, "label": "CO-THEME"}], "edges": [{"source": 4, "target": 18}, {"source": 18, "target": 3}, {"source": 15, "target": 19}, {"source": 19, "target": 14}, {"source": 7, "target": 20}, {"source": 20, "target": 9}, {"source": 15, "target": 21}, {"source": 21, "target": 17}, {"source": 16, "target": 17, "label": "in"}, {"source": 16, "target": 11, "label": "presupposition"}, {"source": 14, "target": 22}, {"source": 22, "target": 2}, {"source": 15, "target": 23}, {"source": 23, "target": 13}, {"source": 3, "target": 24}, {"source": 24, "target": 2}, {"source": 7, "target": 25}, {"source": 25, "target": 10}, {"source": 6, "target": 13, "label": "in"}, {"source": 11, "target": 13, "label": "in"}, {"source": 15, "target": 26}, {"source": 26, "target": 12}, {"source": 4, "target": 27}, {"source": 27, "target": 17}, {"source": 6, "target": 3, "label": "in"}, {"source": 6, "target": 14, "label": "in"}, {"source": 11, "target": 14, "label": "in"}, {"source": 4, "target": 28}, {"source": 28, "target": 14}, {"source": 6, "target": 12, "label": "in"}, {"source": 11, "target": 15, "label": "in"}, {"source": 6, "target": 15, "label": "in"}, {"source": 4, "target": 29}, {"source": 29, "target": 5}, {"source": 16, "target": 6, "label": "presupposition"}, {"source": 11, "target": 12, "label": "in"}, {"source": 11, "target": 3, "label": "in"}, {"source": 1, "target": 9, "label": "in"}, {"source": 6, "target": 5, "label": "in"}, {"source": 0, "target": 9, "label": "in"}, {"source": 7, "target": 30}, {"source": 30, "target": 3}, {"source": 6, "target": 8, "label": "continuation"}, {"source": 11, "target": 6, "label": "attribution"}, {"source": 6, "target": 4, "label": "in"}, {"source": 6, "target": 0, "label": "attribution"}, {"source": 1, "target": 7, "label": "in"}, {"source": 11, "target": 8, "label": "attribution"}, {"source": 4, "target": 31}, {"source": 31, "target": 13}, {"source": 8, "target": 1, "label": "presupposition"}, {"source": 11, "target": 0, "label": "attribution"}, {"source": 0, "target": 7, "label": "in"}], "tops": [11], "framework": "drg", "time": "2025-04-11"}
{"id": "16", "input": "\"He is an Arsenal player and we have to be respectful.", "nodes": [{"id": 0}, {"id": 1}, {"id": 2, "label": "time.n.08"}, {"id": 3, "label": "be.v.08"}, {"id": 4}, {"id": 5, "label": "team.n.01"}, {"id": 6, "label": "\"arsenal\""}, {"id": 7, "label": "person.n.01"}, {"id": 8, "label": "player.n.01"}, {"id": 9}, {"id": 10, "label": "respectful.a.01"}, {"id": 11}, {"id": 12, "label": "\"speaker\""}, {"id": 13, "label": "THEME"}, {"id": 14, "label": "ROLE"}, {"id": 15, "label": "NAME"}, {"id": 16, "label": "TIME"}, {"id": 17, "label": "ATTRIBUTE"}, {"id": 18, "label": "ATTRIBUTE"}, {"id": 19, "label": "CO-THEME"}, {"id": 20, "label": "TIME"}], "edges": [{"source": 3, "target": 13}, {"source": 13, "target": 12}, {"source": 7, "target": 14}, {"source": 14, "target": 8}, {"source": 5, "target": 15}, {"source": 15, "target": 6}, {"source": 3, "target": 16}, {"source": 16, "target": 2}, {"source": 0, "target": 2, "label": "in"}, {"source": 7, "target": 17}, {"source": 17, "target": 10}, {"source": 4, "target": 5, "label": "in"}, {"source": 0, "target": 3, "label": "in"}, {"source": 11, "target": 0, "label": "presupposition"}, {"source": 4, "target": 9, "label": "presupposition"}, {"source": 11, "target": 9, "label": "presupposition"}, {"source": 0, "target": 1, "label": "continuation"}, {"source": 12, "target": 18}, {"source": 18, "target": 10}, {"source": 0, "target": 8, "label": "in"}, {"source": 0, "target": 7, "label": "in"}, {"source": 4, "target": 0, "label": "presupposition"}, {"source": 11, "target": 1, "label": "presupposition"}, {"source": 0, "target": 9, "label": "continuation"}, {"source": 3, "target": 19}, {"source": 19, "target": 7}, {"source": 10, "target": 20}, {"source": 20, "target": 2}, {"source": 1, "target": 8, "label": "in"}, {"source": 9, "target": 10, "label": "in"}], "tops": [0], "framework": "drg", "time": "2025-04-11"}
{"id": "17", "input": "We have to be careful because of the rumours that appear in the news.\"", "nodes": [{"id": 0}, {"id": 1, "label": "\"now\""}, {"id": 2, "label": "time.n.08"}, {"id": 3, "label": "careful.a.01"}, {"id": 4, "label": "rumour.n.01"}, {"id": 5, "label": "appear.v.01"}, {"id": 6}, {"id": 7, "label": "news.n.01"}, {"id": 8}, {"id": 9, "label": "\"speaker\""}, {"id": 10, "label": "EQU"}, {"id": 11, "label": "EXPERIENCER"}, {"id": 12, "label": "THEME"}, {"id": 13, "label": "THEME"}, {"id": 14, "label": "THEME"}, {"id": 15, "label": "TIME"}], "edges": [{"source": 0, "target": 3, "label": "in"}, {"source": 2, "target": 10}, {"source": 10, "target": 1}, {"source": 0, "target": 4, "label": "in"}, {"source": 8, "target": 0, "label": "attribution"}, {"source": 3, "target": 11}, {"source": 11, "target": 9}, {"source": 5, "target": 12}, {"source": 12, "target": 7}, {"source": 6, "target": 7, "label": "in"}, {"source": 8, "target": 2, "label": "in"}, {"source": 5, "target": 13}, {"source": 13, "target": 4}, {"source": 6, "target": 0, "label": "presupposition"}, {"source": 4, "target": 14}, {"source": 14, "target": 7}, {"source": 5, "target": 15}, {"source": 15, "target": 2}], "tops": [8], "framework": "drg", "time": "2025-04-11"}
